odoo9_addon_delivery_roulier-9.0.2.0.0-py2.7-nspkg.pth
odoo9_addon_delivery_roulier-9.0.2.0.0.dist-info/DESCRIPTION.rst
odoo9_addon_delivery_roulier-9.0.2.0.0.dist-info/METADATA
odoo9_addon_delivery_roulier-9.0.2.0.0.dist-info/RECORD
odoo9_addon_delivery_roulier-9.0.2.0.0.dist-info/WHEEL
odoo9_addon_delivery_roulier-9.0.2.0.0.dist-info/metadata.json
odoo9_addon_delivery_roulier-9.0.2.0.0.dist-info/namespace_packages.txt
odoo9_addon_delivery_roulier-9.0.2.0.0.dist-info/top_level.txt
odoo_addons/delivery_roulier/README.rst
odoo_addons/delivery_roulier/__init__.py
odoo_addons/delivery_roulier/__openerp__.py
odoo_addons/delivery_roulier/models/__init__.py
odoo_addons/delivery_roulier/models/stock_picking.py
odoo_addons/delivery_roulier/models/stock_quant_package.py
odoo_addons/delivery_roulier/views/stock_quant_package.xml
