Metadata-Version: 2.0
Name: odoo9-addon-delivery-roulier
Version: 9.0.2.0.0
Summary: Integration of multiple carriers
Home-page: https://akretion.com/
Author: Akretion,Odoo Community Association (OCA)
Author-email: support@odoo-community.org
License: AGPL-3
Platform: UNKNOWN
Classifier: Programming Language :: Python
Classifier: Framework :: Odoo
Classifier: License :: OSI Approved :: GNU Affero General Public License v3
Requires-Python: ~=2.7
Requires-Dist: odoo (<9.1a,>=9.0a)
Requires-Dist: odoo9-addon-base-delivery-carrier-label
Requires-Dist: odoo9-addon-base-phone
Requires-Dist: odoo9-addon-base-suspend-security
Requires-Dist: odoo9-addon-delivery-carrier-deposit
Requires-Dist: odoo9-addon-keychain
Requires-Dist: odoo9-addon-partner-helper
Requires-Dist: odoo9-addon-product-harmonized-system
Requires-Dist: roulier
